mwgapp/__init__.py
mwgapp/build.py
mwgapp/exceptions.py
mwgapp/git.py
mwgapp/main.py
mwgapp/plans.py
mwgapp/terraform.py
mwgapp-0.0.10.dist-info/METADATA
mwgapp-0.0.10.dist-info/WHEEL
mwgapp-0.0.10.dist-info/entry_points.txt
mwgapp-0.0.10.dist-info/RECORD
