Metadata-Version: 2.1
Name: mwgapp
Version: 0.0.10
Author-email: chriswacker <christopher.wacker@goaaa.com>
Requires-Python: >=3.7
Requires-Dist: google-cloud-storage
